boask/__init__.py
boask/core.py
boask/error.py
boask/version.py
boask/auth/ban.py
boask/auth/banlist.py
boask/auth/login.py
boask/auth/register.py
boask/auth/users.py
boask/middleware/advanced_auth.py
boask/middleware/auth.py
boask/middleware/basic_auth.py
boask/middleware/cors.py
boask/middleware/logging.py
boask/middleware/rate_limit.py
boask/templates/html.py
boask-1.2.0.dist-info/METADATA
boask-1.2.0.dist-info/WHEEL
boask-1.2.0.dist-info/top_level.txt
boask-1.2.0.dist-info/RECORD
