Metadata-Version: 2.4
Name: boask
Version: 1.2.0
Summary: Pure Python website engine. Zero dependencies. Real JSX templates.
Author: OXOP
Author-email: minbartek41@gmail.com
License: MIT
Keywords: web,minimal,python,no-dependencies
Classifier: Programming Language :: Python :: 3
Classifier: Operating System :: OS Independent
Requires-Python: >=3.8
Requires-Dist: Werkzeug>=2.3.0
Requires-Dist: PyJWT>=2.8.0
Dynamic: author
Dynamic: author-email
Dynamic: classifier
Dynamic: description
Dynamic: description-content-type
Dynamic: keywords
Dynamic: license
Dynamic: requires-dist
Dynamic: requires-python
Dynamic: summary
